pyturbo_sf/__init__.py
pyturbo_sf/bessel_tools.py
pyturbo_sf/binning_tools.py
pyturbo_sf/bootstrapping_tools.py
pyturbo_sf/core.py
pyturbo_sf/isotropy_tools.py
pyturbo_sf/one_dimensional.py
pyturbo_sf/structure_functions.py
pyturbo_sf/three_dimensional.py
pyturbo_sf/two_dimensional.py
pyturbo_sf/utils.py
pyturbo_sf-1.0.7.dist-info/licenses/LICENSE
pyturbo_sf-1.0.7.dist-info/METADATA
pyturbo_sf-1.0.7.dist-info/WHEEL
pyturbo_sf-1.0.7.dist-info/top_level.txt
pyturbo_sf-1.0.7.dist-info/RECORD
