Metadata-Version: 2.4
Name: pyturbo_sf
Version: 1.0.7
Summary: Python Turbulence Unleashed: Rapid Binning Operator
Author-email: Adam Ayouche <adam_ayouche@brown.edu>
Project-URL: Homepage, https://github.com/aayouche/pyturbo_sf
Project-URL: Bug Tracker, https://github.com/aayouche/pyturbo_sf/issues
Classifier: Development Status :: 3 - Alpha
Classifier: Intended Audience :: Science/Research
Classifier: License :: OSI Approved :: MIT License
Classifier: Programming Language :: Python :: 3
Classifier: Programming Language :: Python :: 3.11
Classifier: Programming Language :: Python :: 3.12
Classifier: Programming Language :: Python :: 3.13
Classifier: Programming Language :: Python :: 3.14
Classifier: Topic :: Scientific/Engineering :: Physics
Requires-Python: >=3.11
License-File: LICENSE
Requires-Dist: numpy>=1.24.0
Requires-Dist: scipy>=1.16.2
Requires-Dist: xarray>=2025.12.0
Requires-Dist: matplotlib>=3.10.7
Requires-Dist: bottleneck>=1.6.0
Requires-Dist: joblib>=1.5.2
Provides-Extra: dev
Requires-Dist: pytest>=9.0.0; extra == "dev"
Requires-Dist: pytest-cov>=7.0.0; extra == "dev"
Requires-Dist: black>=25.0.0; extra == "dev"
Requires-Dist: isort>=6.0.0; extra == "dev"
Requires-Dist: flake8>=7.3.0; extra == "dev"
Requires-Dist: memory_profiler>=0.61.0; extra == "dev"
Provides-Extra: docs
Requires-Dist: sphinx<9.0.0,>=6.0.0; extra == "docs"
Requires-Dist: sphinx-rtd-theme>=3.0.2; extra == "docs"
Requires-Dist: nbsphinx>=0.9.8; extra == "docs"
Requires-Dist: ipython>=8.30.0; extra == "docs"
Provides-Extra: extras
Requires-Dist: pyproj; extra == "extras"
Requires-Dist: tqdm; extra == "extras"
Requires-Dist: h5netcdf; extra == "extras"
Requires-Dist: netcdf4; extra == "extras"
Requires-Dist: jupyter; extra == "extras"
Provides-Extra: complete
Requires-Dist: pyturbo_sf[dev,docs,extras]; extra == "complete"
Dynamic: license-file
